hik_robot_cam/__init__.py
hik_robot_cam/hik_robot_cam.cpython-312-x86_64-linux-gnu.so
hik_robot_cam/hik_robot_cam.pyi
hik_robot_cam.libs/libMvCameraControl-642b9499.so.4.5.0.3
hik_robot_cam.libs/libopencv_calib3d-f7a8250b.so.4.5.4d
hik_robot_cam.libs/libopencv_core-8baa4de0.so.4.5.4d
hik_robot_cam.libs/libopencv_features2d-b1766977.so.4.5.4d
hik_robot_cam.libs/libopencv_flann-20f3b3c8.so.4.5.4d
hik_robot_cam.libs/libopencv_imgproc-33dba9de.so.4.5.4d
hik_robot_cam.libs/libopencv_stitching-dbb5d50f.so.4.5.4d
hik_robot_cam.libs/libtbb-b87fa093.so.2
hik_robot_cam-0.1.3.post1.dist-info/METADATA
hik_robot_cam-0.1.3.post1.dist-info/WHEEL
hik_robot_cam-0.1.3.post1.dist-info/RECORD
hik_robot_cam-0.1.3.post1.dist-info/licenses/LICENSE
