Metadata-Version: 2.1
Name: hik-robot-cam
Version: 0.1.3.post1
Summary: Python wrapper for Hik Camera SDK using pybind11
License: MIT
Classifier: Programming Language :: C++
Classifier: Programming Language :: Python :: 3 :: Only
Classifier: Programming Language :: Python :: 3.7
Classifier: Programming Language :: Python :: 3.8
Classifier: Programming Language :: Python :: 3.9
Classifier: Programming Language :: Python :: 3.10
Classifier: Programming Language :: Python :: 3.11
Classifier: Programming Language :: Python :: 3.12
Classifier: License :: OSI Approved :: MIT License
Requires-Python: >=3.8
Requires-Dist: opencv-python>=4.6
Requires-Dist: numpy
